zhanshop/aes.py
zhanshop/app.py
zhanshop/cache.py
zhanshop/chrome.py
zhanshop/config.py
zhanshop/controller.py
zhanshop/database.py
zhanshop/env.py
zhanshop/error.py
zhanshop/flock.py
zhanshop/hash.py
zhanshop/httpclient.py
zhanshop/json.py
zhanshop/log.py
zhanshop/middleware.py
zhanshop/model.py
zhanshop/office.py
zhanshop/route.py
zhanshop/schema.py
zhanshop/server.py
zhanshop/socket.py
zhanshop/validate.py
zhanshop/console/apidoc.py
zhanshop/console/help.py
zhanshop/db/connection.py
zhanshop/db/query.py
zhanshop/db/builder/__init__.py
zhanshop/db/builder/mysql.py
zhanshop/docker/container.py
zhanshop/docker/engineapi.py
zhanshop/docker/images.py
zhanshop/docker/network.py
zhanshop/docker/volume.py
zhanshop/helper/System.py
zhanshop/helper/annotations.py
zhanshop/helper/array.py
zhanshop/helper/file.py
zhanshop/helper/str.py
zhanshop/helper/varcheck.py
zhanshop_py-1.0.0.dist-info/LICENSE
zhanshop_py-1.0.0.dist-info/METADATA
zhanshop_py-1.0.0.dist-info/WHEEL
zhanshop_py-1.0.0.dist-info/top_level.txt
zhanshop_py-1.0.0.dist-info/RECORD
