Metadata-Version: 2.1
Name: zhanshop-py
Version: 1.0.0
Summary: 张启全的python框架
Author: 张启全
Author-email: admin@zhanshop.cn
Requires-Python: >=3.10
License-File: LICENSE
Requires-Dist: flask
Requires-Dist: flask-redis
Requires-Dist: pymysql
Requires-Dist: pycryptodome
Requires-Dist: qiniu
Requires-Dist: apscheduler
